libgunshotmatch_mpl/__init__.py
libgunshotmatch_mpl/chromatogram.py
libgunshotmatch_mpl/combined_chromatogram.py
libgunshotmatch_mpl/peakviewer.py
libgunshotmatch_mpl/py.typed
libgunshotmatch_mpl-0.8.0.dist-info/LICENSE
libgunshotmatch_mpl-0.8.0.dist-info/METADATA
libgunshotmatch_mpl-0.8.0.dist-info/WHEEL
libgunshotmatch_mpl-0.8.0.dist-info/entry_points.txt
libgunshotmatch_mpl-0.8.0.dist-info/RECORD
