Metadata-Version: 2.2
Name: libgunshotmatch-mpl
Version: 0.8.0
Summary: Matplotlib intergration for GunShotMatch.
Author-email: Dominic Davis-Foster <dominic@davis-foster.co.uk>
License: MIT
Home-page: https://github.com/GunShotMatch/libgunshotmatch-mpl
Project-URL: Issue Tracker, https://github.com/GunShotMatch/libgunshotmatch-mpl/issues
Project-URL: Source Code, https://github.com/GunShotMatch/libgunshotmatch-mpl
Project-URL: Documentation, https://libgunshotmatch-mpl.readthedocs.io/en/latest
Platform: Windows
Platform: macOS
Platform: Linux
Classifier: Development Status :: 3 - Alpha
Classifier: Intended Audience :: Developers
Classifier: License :: OSI Approved :: MIT License
Classifier: Operating System :: OS Independent
Classifier: Programming Language :: Python
Classifier: Programming Language :: Python :: 3 :: Only
Classifier: Programming Language :: Python :: 3.8
Classifier: Programming Language :: Python :: 3.9
Classifier: Programming Language :: Python :: 3.10
Classifier: Programming Language :: Python :: 3.11
Classifier: Programming Language :: Python :: 3.12
Classifier: Programming Language :: Python :: Implementation :: CPython
Classifier: Topic :: Software Development :: Libraries :: Python Modules
Classifier: Typing :: Typed
Requires-Python: >=3.8
Requires-Dist: domdf-python-tools>=3.8.0.post2
Requires-Dist: libgunshotmatch>=0.7.0
Requires-Dist: matplotlib>=3.7.2
Requires-Dist: numpy>=1.24.4
Requires-Dist: textalloc>=0.0.9
